README
setup.cfg
setup.py
oulinbao/__init__.py
oulinbao/main.py
oulinbao.egg-info/PKG-INFO
oulinbao.egg-info/SOURCES.txt
oulinbao.egg-info/dependency_links.txt
oulinbao.egg-info/top_level.txt