Metadata-Version: 1.1
Name: oulinbao
Version: 0.0.9
Summary: oulinbao test pypi
Home-page: https://pypi.org/project/oulinbao/
Author: oulinbao
Author-email: UNKNOWN
License: UNKNOWN
Platform: UNKNOWN
Classifier: Programming Language :: Python :: 2
Classifier: Programming Language :: Python :: 2.7
